odoo8_addon_stock_picking_invoice_product_group-8.0.1.0.0.99.dev4-py2.7-nspkg.pth
odoo_addons/stock_picking_invoice_product_group/__openerp__.py
odoo_addons/stock_picking_invoice_product_group/__init__.py
odoo_addons/stock_picking_invoice_product_group/README.rst
odoo_addons/stock_picking_invoice_product_group/i18n/it.po
odoo_addons/stock_picking_invoice_product_group/i18n/es.po
odoo_addons/stock_picking_invoice_product_group/i18n/tr.po
odoo_addons/stock_picking_invoice_product_group/i18n/sl.po
odoo_addons/stock_picking_invoice_product_group/i18n/de.po
odoo_addons/stock_picking_invoice_product_group/i18n/fr.po
odoo_addons/stock_picking_invoice_product_group/wizards/stock_invoice_onshipping.py
odoo_addons/stock_picking_invoice_product_group/wizards/stock_invoice_onshipping_view.xml
odoo_addons/stock_picking_invoice_product_group/wizards/__init__.py
odoo_addons/stock_picking_invoice_product_group/tests/__init__.py
odoo_addons/stock_picking_invoice_product_group/tests/test_invoice_product_group.py
odoo_addons/stock_picking_invoice_product_group/demo/product.xml
odoo_addons/stock_picking_invoice_product_group/static/description/icon.png
odoo8_addon_stock_picking_invoice_product_group-8.0.1.0.0.99.dev4.dist-info/top_level.txt
odoo8_addon_stock_picking_invoice_product_group-8.0.1.0.0.99.dev4.dist-info/WHEEL
odoo8_addon_stock_picking_invoice_product_group-8.0.1.0.0.99.dev4.dist-info/RECORD
odoo8_addon_stock_picking_invoice_product_group-8.0.1.0.0.99.dev4.dist-info/metadata.json
odoo8_addon_stock_picking_invoice_product_group-8.0.1.0.0.99.dev4.dist-info/DESCRIPTION.rst
odoo8_addon_stock_picking_invoice_product_group-8.0.1.0.0.99.dev4.dist-info/METADATA
odoo8_addon_stock_picking_invoice_product_group-8.0.1.0.0.99.dev4.dist-info/namespace_packages.txt
